graphai_client/__init__.py
graphai_client/client.py
graphai_client/utils.py
graphai_client/client_api/__init__.py
graphai_client/client_api/embedding.py
graphai_client/client_api/image.py
graphai_client/client_api/text.py
graphai_client/client_api/translation.py
graphai_client/client_api/utils.py
graphai_client/client_api/video.py
graphai_client/client_api/voice.py
graphai_client/rcp/__init__.py
graphai_client/rcp/detect_concepts_for_courses.py
graphai_client/rcp/detect_concepts_for_persons.py
graphai_client/rcp/detect_concepts_for_publications.py
graphai_client/rcp/detect_concepts_for_videos.py
graphai_client/rcp/detect_slides.py
graphai_client/rcp/embed_concepts.py
graphai_client/rcp/get_video_info.py
graphai_client/rcp/process_audio.py
graphai_client/rcp/translate_slides.py
graphai_client/tests/captions.py
graphai_client/tests/text.py
graphai_client/tests/translation.py
graphai_client/tests/voice.py
graphai_client/tests/test_files/0_00w4rf3f_en.srt
graphai_client/tests/test_files/0_00w4rf3f_fr.srt
graphai_client/tests/test_files/0_iz3wgt1s_en.srt
graphai_client/tests/test_files/0_iz3wgt1s_fr.srt
graphai_client/tests/test_files/0_vvgduz0b_en.srt
graphai_client/tests/test_files/0_vvgduz0b_fr.srt
graphai_client-1.16.0.dist-info/METADATA
graphai_client-1.16.0.dist-info/WHEEL
graphai_client-1.16.0.dist-info/licenses/LICENSE
graphai_client-1.16.0.dist-info/RECORD
