Metadata-Version: 2.4
Name: graphai_client
Version: 1.16.0
Summary: A client library to access the graphai services
Project-URL: Homepage, https://github.com/epflgraph/graphai-client
Project-URL: Bug Tracker, https://github.com/epflgraph/graphai-client/issues
Author-email: Renier Yves <yves.renier@epfl.ch>
License-File: LICENSE
Classifier: License :: OSI Approved :: GNU General Public License v3 or later (GPLv3+)
Classifier: Operating System :: OS Independent
Classifier: Programming Language :: Python :: 3
Requires-Python: >=3.8
Requires-Dist: google-api-python-client
Requires-Dist: isodate
Requires-Dist: mysql-connector-python>=9.2.0
Requires-Dist: termcolor
